devantech_eth/__init__.py
devantech_eth/eth002.py
devantech_eth/eth008.py
devantech_eth/eth484.py
devantech_eth/eth8020.py
devantech_eth/module_socket.py
devantech_eth-0.1.2.dist-info/LICENSE
devantech_eth-0.1.2.dist-info/METADATA
devantech_eth-0.1.2.dist-info/WHEEL
devantech_eth-0.1.2.dist-info/top_level.txt
devantech_eth-0.1.2.dist-info/RECORD
