Metadata-Version: 2.1
Name: devantech-eth
Version: 0.1.2
Summary: Python library for controlling Devantech ETH modules.
Home-page: UNKNOWN
Author: James Henderson
License: MIT
Platform: UNKNOWN
License-File: LICENSE
